pytmler/__init__.py
pytmler/pytmler.py
pytmler-0.1.3.dist-info/LICENCE.txt
pytmler-0.1.3.dist-info/METADATA
pytmler-0.1.3.dist-info/WHEEL
pytmler-0.1.3.dist-info/top_level.txt
pytmler-0.1.3.dist-info/RECORD
